{
  "rows_compared": 4000,
  "average": {
    "correlation": 0.6510515805100756,
    "KL": Infinity,
    "JS": 0.040945681743699065
  },
  "per_question": [
    {
      "correlation": NaN,
      "KL": 0.0,
      "JS": 0.0,
      "question_id": "A1"
    },
    {
      "correlation": 1.0,
      "KL": 0.1040731157106119,
      "JS": 0.02829981863064759,
      "question_id": "A10"
    },
    {
      "correlation": 0.9989975494663338,
      "KL": Infinity,
      "JS": 0.006620457541211026,
      "question_id": "A2"
    },
    {
      "correlation": NaN,
      "KL": 0.0,
      "JS": 0.0,
      "question_id": "A3"
    },
    {
      "correlation": 1.0,
      "KL": 0.015229583210289381,
      "JS": 0.0035056611292696087,
      "question_id": "A4"
    },
    {
      "correlation": 1.0,
      "KL": Infinity,
      "JS": 0.013175660665944243,
      "question_id": "A5"
    },
    {
      "correlation": 0.9276068186109516,
      "KL": Infinity,
      "JS": 0.019742302919945175,
      "question_id": "A6"
    },
    {
      "correlation": 1.0,
      "KL": 0.032535931484338546,
      "JS": 0.006204736600455902,
      "question_id": "A7"
    },
    {
      "correlation": 1.0,
      "KL": 0.00886153728837133,
      "JS": 0.0023039255334570585,
      "question_id": "A8"
    },
    {
      "correlation": -1.0,
      "KL": 0.1712030266485143,
      "JS": 0.04406239474476195,
      "question_id": "A9"
    },
    {
      "correlation": 0.9336526918025052,
      "KL": Infinity,
      "JS": 0.012068833588590537,
      "question_id": "C1"
    },
    {
      "correlation": 0.5085362993432483,
      "KL": Infinity,
      "JS": 0.09438455724304283,
      "question_id": "C10"
    },
    {
      "correlation": 0.9989463292737499,
      "KL": 0.1598245680754845,
      "JS": 0.05089851400570378,
      "question_id": "C2"
    },
    {
      "correlation": 0.4125103994951046,
      "KL": Infinity,
      "JS": 0.17949621215807193,
      "question_id": "C3"
    },
    {
      "correlation": 0.9932012920867158,
      "KL": 0.07881685957175527,
      "JS": 0.023517847468871474,
      "question_id": "C4"
    },
    {
      "correlation": 0.9988960613088314,
      "KL": 0.00032853624169601817,
      "JS": 8.205699467122696e-05,
      "question_id": "C5"
    },
    {
      "correlation": 0.32058357172200347,
      "KL": 0.022080249714216404,
      "JS": 0.005584142033074907,
      "question_id": "C6"
    },
    {
      "correlation": 0.9954153064271758,
      "KL": Infinity,
      "JS": 0.007726148749150602,
      "question_id": "C7"
    },
    {
      "correlation": 1.0,
      "KL": Infinity,
      "JS": 0.008743455793932313,
      "question_id": "C8"
    },
    {
      "correlation": 0.8405009683312461,
      "KL": Infinity,
      "JS": 0.05093330541985406,
      "question_id": "C9"
    },
    {
      "correlation": 0.5868743494691295,
      "KL": 0.12170955777885965,
      "JS": 0.02943209128231374,
      "question_id": "E1"
    },
    {
      "correlation": 0.9785822419121805,
      "KL": Infinity,
      "JS": 0.027319297078191092,
      "question_id": "E10"
    },
    {
      "correlation": 0.24836494685418142,
      "KL": 0.4927177453963395,
      "JS": 0.12467038068561336,
      "question_id": "E2"
    },
    {
      "correlation": 0.9958612892059577,
      "KL": Infinity,
      "JS": 0.005467659129214668,
      "question_id": "E3"
    },
    {
      "correlation": 0.7646996629670358,
      "KL": Infinity,
      "JS": 0.15902293408166537,
      "question_id": "E4"
    },
    {
      "correlation": 0.5290459278023742,
      "KL": 0.23173339858314845,
      "JS": 0.05730277292355889,
      "question_id": "E5"
    },
    {
      "correlation": 0.9918694457127308,
      "KL": Infinity,
      "JS": 0.04189748935241981,
      "question_id": "E6"
    },
    {
      "correlation": 0.8228973104004178,
      "KL": 0.11132013118248794,
      "JS": 0.02568034963334603,
      "question_id": "E7"
    },
    {
      "correlation": 0.026875506440096158,
      "KL": 0.5271053050315138,
      "JS": 0.12288257094230358,
      "question_id": "E8"
    },
    {
      "correlation": 0.47136572685434974,
      "KL": 0.08312845270941843,
      "JS": 0.020158744818897224,
      "question_id": "E9"
    },
    {
      "correlation": -0.42504840755701107,
      "KL": 0.1302478024369652,
      "JS": 0.03379179251338309,
      "question_id": "N1"
    },
    {
      "correlation": 0.8912799708493745,
      "KL": 0.545148999153829,
      "JS": 0.08094027771495176,
      "question_id": "N10"
    },
    {
      "correlation": 0.9973828402029646,
      "KL": 0.01907188662094097,
      "JS": 0.003992157129980981,
      "question_id": "N2"
    },
    {
      "correlation": 0.9557422975723062,
      "KL": 0.20619798843071852,
      "JS": 0.04438330050555126,
      "question_id": "N3"
    },
    {
      "correlation": -1.0,
      "KL": 0.5677363608844899,
      "JS": 0.13848329231180356,
      "question_id": "N4"
    },
    {
      "correlation": 0.9711837655967623,
      "KL": Infinity,
      "JS": 0.009048804145249691,
      "question_id": "N5"
    },
    {
      "correlation": 0.9925433834391968,
      "KL": Infinity,
      "JS": 0.01874771822336135,
      "question_id": "N6"
    },
    {
      "correlation": 0.3995859499014601,
      "KL": 0.27946305046221914,
      "JS": 0.06970036313694442,
      "question_id": "N7"
    },
    {
      "correlation": 0.9990969080325487,
      "KL": 0.2598057053603233,
      "JS": 0.040628354696594475,
      "question_id": "N8"
    },
    {
      "correlation": 0.9995727797967877,
      "KL": Infinity,
      "JS": 0.004993692269259588,
      "question_id": "N9"
    },
    {
      "correlation": 0.29741597829733113,
      "KL": 0.35793630560708767,
      "JS": 0.0886407996765712,
      "question_id": "O1"
    },
    {
      "correlation": 0.9624990616211377,
      "KL": 0.03494866798260218,
      "JS": 0.009008740060711473,
      "question_id": "O10"
    },
    {
      "correlation": 0.9868535297205628,
      "KL": 0.03955932313004398,
      "JS": 0.01061865101995488,
      "question_id": "O2"
    },
    {
      "correlation": 0.25408540454984785,
      "KL": 0.2021528835886563,
      "JS": 0.05175597579050985,
      "question_id": "O3"
    },
    {
      "correlation": 0.9905828520621208,
      "KL": 0.09272822028741193,
      "JS": 0.018025133470458463,
      "question_id": "O4"
    },
    {
      "correlation": 0.9165196849491712,
      "KL": Infinity,
      "JS": 0.018978005261833308,
      "question_id": "O5"
    },
    {
      "correlation": 0.9957417349280381,
      "KL": Infinity,
      "JS": 0.009383091952272077,
      "question_id": "O6"
    },
    {
      "correlation": -1.0,
      "KL": 0.11576846135022931,
      "JS": 0.029567243217296188,
      "question_id": "O7"
    },
    {
      "correlation": -0.18052985408835553,
      "KL": 0.7158790716469697,
      "JS": 0.17278792269644655,
      "question_id": "O8"
    },
    {
      "correlation": 0.9006842891230669,
      "KL": 0.08011096530187789,
      "JS": 0.02262445024363911,
      "question_id": "O9"
    }
  ]
}